{
    "ARS": [
        {
            "name": "Rice",
            "arima": 28.091541688799424,
            "lstm": 27.876712328767116,
            "actual_points": 27
        },
        {
            "name": "G.Jesus",
            "arima": 40.758620689655196,
            "lstm": 34.69827586206896,
            "actual_points": 33
        },
        {
            "name": "Zinchenko",
            "arima": 32.50000000000001,
            "lstm": 30.723684210526308,
            "actual_points": 46
        },
        {
            "name": "Saka",
            "arima": 57.637579753496865,
            "lstm": 34.49074074074073,
            "actual_points": 43
        },
        {
            "name": "Trossard",
            "arima": 38.26119431781776,
            "lstm": 40.4370364856924,
            "actual_points": 26
        },
        {
            "name": "Havertz",
            "arima": 31.89473684210529,
            "lstm": 33.784301606134825,
            "actual_points": 32
        },
        {
            "name": "Ødegaard",
            "arima": 58.45676570930899,
            "lstm": 36.142857142857146,
            "actual_points": 40
        },
        {
            "name": "Raya",
            "arima": 42.46153846153848,
            "lstm": 34.32692307692307,
            "actual_points": 31
        },
        {
            "name": "Saliba",
            "arima": 42.36332393980499,
            "lstm": 35.17857142857143,
            "actual_points": 31
        },
        {
            "name": "White",
            "arima": 42.666666666666664,
            "lstm": 34.16666666666667,
            "actual_points": 24
        },
        {
            "name": "Martinelli",
            "arima": 50.476190476190446,
            "lstm": 48.98587491181696,
            "actual_points": 30
        },
        {
            "name": "Nketiah",
            "arima": 24.324324324324337,
            "lstm": 25.517241379310352,
            "actual_points": 30
        },
        {
            "name": "Gabriel",
            "arima": 36.36363636363636,
            "lstm": 32.86115053581797,
            "actual_points": 33
        }
    ],
    "AVL": [
        {
            "name": "Digne",
            "arima": 26.639619783527202,
            "lstm": 33.836083435049844,
            "actual_points": 28
        },
        {
            "name": "Tielemans",
            "arima": 32.894736842105246,
            "lstm": 32.190082644628106,
            "actual_points": 23
        },
        {
            "name": "Douglas Luiz",
            "arima": 52.83070811562414,
            "lstm": 27.389380530973458,
            "actual_points": 45
        },
        {
            "name": "McGinn",
            "arima": 30.0,
            "lstm": 29.495412844036693,
            "actual_points": 39
        },
        {
            "name": "Konsa",
            "arima": 28.63636363636363,
            "lstm": 28.761904761904763,
            "actual_points": 22
        },
        {
            "name": "Watkins",
            "arima": 45.39823008849559,
            "lstm": 35.5,
            "actual_points": 48
        },
        {
            "name": "Bailey",
            "arima": 29.13793103448276,
            "lstm": 27.93478260869566,
            "actual_points": 41
        },
        {
            "name": "Martinez",
            "arima": 34.21100179495121,
            "lstm": 31.85714285714286,
            "actual_points": 35
        },
        {
            "name": "Diaby",
            "arima": 0,
            "lstm": 0,
            "actual_points": 28
        },
        {
            "name": "Pau",
            "arima": 0,
            "lstm": 0,
            "actual_points": 30
        }
    ],
    "BOU": [
        {
            "name": "Smith",
            "arima": 22.325581395348852,
            "lstm": 26.617647058823525,
            "actual_points": 32
        },
        {
            "name": "Billing",
            "arima": 26.019523386265504,
            "lstm": 26.92771084337349,
            "actual_points": 33
        },
        {
            "name": "L.Cook",
            "arima": 16.917978066578197,
            "lstm": 23.771929824561404,
            "actual_points": 22
        },
        {
            "name": "Solanke",
            "arima": 38.826312940707986,
            "lstm": 27.196969696969692,
            "actual_points": 59
        },
        {
            "name": "Christie",
            "arima": 19.75000000000001,
            "lstm": 24.375,
            "actual_points": 28
        },
        {
            "name": "Tavernier",
            "arima": 35.450214649362174,
            "lstm": 39.96119632531797,
            "actual_points": 46
        },
        {
            "name": "Senesi",
            "arima": 21.47850925299631,
            "lstm": 26.379310344827584,
            "actual_points": 48
        },
        {
            "name": "Neto",
            "arima": 36.916745761746974,
            "lstm": 35.512581833600166,
            "actual_points": 42
        },
        {
            "name": "Semenyo",
            "arima": 20.000000000000004,
            "lstm": 25.833333333333332,
            "actual_points": 32
        },
        {
            "name": "Zabarnyi",
            "arima": 13.571428571428575,
            "lstm": 22.27272727272727,
            "actual_points": 30
        },
        {
            "name": "Kluivert",
            "arima": 0,
            "lstm": 0,
            "actual_points": 33
        },
        {
            "name": "Kerkez",
            "arima": 0,
            "lstm": 0,
            "actual_points": 21
        }
    ],
    "BRE": [
        {
            "name": "Maupay",
            "arima": 16.203185761654982,
            "lstm": 30.817307692307697,
            "actual_points": 31
        },
        {
            "name": "Pinnock",
            "arima": 31.9402985074627,
            "lstm": 29.36000368945285,
            "actual_points": 26
        },
        {
            "name": "Janelt",
            "arima": 26.666666666666643,
            "lstm": 27.017543859649116,
            "actual_points": 23
        },
        {
            "name": "Mbeumo",
            "arima": 38.79999999999998,
            "lstm": 33.91653663409784,
            "actual_points": 52
        },
        {
            "name": "Wissa",
            "arima": 33.35127721001346,
            "lstm": 28.1896551724138,
            "actual_points": 23
        },
        {
            "name": "Jensen",
            "arima": 38.153782737897544,
            "lstm": 27.222222222222218,
            "actual_points": 42
        },
        {
            "name": "Collins",
            "arima": 23.75000000000001,
            "lstm": 26.315789473684212,
            "actual_points": 27
        },
        {
            "name": "Flekken",
            "arima": 0,
            "lstm": 0,
            "actual_points": 23
        }
    ],
    "BHA": [
        {
            "name": "Gross",
            "arima": 34.50980392156861,
            "lstm": 31.516393442622956,
            "actual_points": 46
        },
        {
            "name": "Welbeck",
            "arima": 30.109214852059583,
            "lstm": 31.572175944464348,
            "actual_points": 28
        },
        {
            "name": "João Pedro",
            "arima": 22.000000000000004,
            "lstm": 25.0,
            "actual_points": 44
        },
        {
            "name": "Steele",
            "arima": 41.666666666666686,
            "lstm": 43.94436210625976,
            "actual_points": 25
        },
        {
            "name": "Ferguson",
            "arima": 31.200000000000006,
            "lstm": 28.98463948678867,
            "actual_points": 28
        },
        {
            "name": "Mitoma",
            "arima": 44.57142857142856,
            "lstm": 34.46428571428572,
            "actual_points": 23
        },
        {
            "name": "Adingra",
            "arima": 0,
            "lstm": 0,
            "actual_points": 33
        }
    ],
    "BUR": [
        {
            "name": "Taylor",
            "arima": 26.803278688524582,
            "lstm": 28.556701030927837,
            "actual_points": 28
        },
        {
            "name": "Berge",
            "arima": 22.972972972972986,
            "lstm": 27.241379310344833,
            "actual_points": 22
        },
        {
            "name": "Brownhill",
            "arima": 23.291139240506325,
            "lstm": 25.396825396825392,
            "actual_points": 31
        },
        {
            "name": "Koleosho",
            "arima": 0,
            "lstm": 0,
            "actual_points": 28
        },
        {
            "name": "Trafford",
            "arima": 0,
            "lstm": 0,
            "actual_points": 37
        },
        {
            "name": "Amdouni",
            "arima": 0,
            "lstm": 0,
            "actual_points": 34
        },
        {
            "name": "Beyer",
            "arima": 0,
            "lstm": 0,
            "actual_points": 26
        }
    ],
    "CHE": [
        {
            "name": "Sterling",
            "arima": 46.54018170888144,
            "lstm": 57.95771280433762,
            "actual_points": 36
        },
        {
            "name": "Gallagher",
            "arima": 26.5229291181938,
            "lstm": 28.475609756097562,
            "actual_points": 26
        },
        {
            "name": "Sanchez",
            "arima": 35.73033707865167,
            "lstm": 32.739860126112305,
            "actual_points": 33
        },
        {
            "name": "Palmer",
            "arima": 20.225029238530617,
            "lstm": 18.68421052631579,
            "actual_points": 65
        },
        {
            "name": "T.Silva",
            "arima": 34.53124999999999,
            "lstm": 32.64546174592756,
            "actual_points": 23
        },
        {
            "name": "Colwill",
            "arima": 29.600000000000005,
            "lstm": 27.574935979967485,
            "actual_points": 20
        },
        {
            "name": "Mudryk",
            "arima": 18.99999999999999,
            "lstm": 22.8125,
            "actual_points": 39
        },
        {
            "name": "Enzo",
            "arima": 23.47826086956522,
            "lstm": 25.833333333333332,
            "actual_points": 31
        },
        {
            "name": "N.Jackson",
            "arima": 0,
            "lstm": 0,
            "actual_points": 45
        }
    ],
    "CRY": [
        {
            "name": "Schlupp",
            "arima": 26.760563380281678,
            "lstm": 28.407079646017696,
            "actual_points": 26
        },
        {
            "name": "Ward",
            "arima": 23.067391592793882,
            "lstm": 27.57731958762886,
            "actual_points": 20
        },
        {
            "name": "J.Ayew",
            "arima": 27.360353366173122,
            "lstm": 28.500000000000007,
            "actual_points": 35
        },
        {
            "name": "Mitchell",
            "arima": 27.91852177390909,
            "lstm": 28.924050632911392,
            "actual_points": 29
        },
        {
            "name": "Eze",
            "arima": 36.7857142857143,
            "lstm": 32.25195233667451,
            "actual_points": 34
        },
        {
            "name": "Johnstone",
            "arima": 36.47058823529412,
            "lstm": 33.625,
            "actual_points": 36
        },
        {
            "name": "Mateta",
            "arima": 21.290322580645157,
            "lstm": 25.306122448979593,
            "actual_points": 29
        },
        {
            "name": "Guéhi",
            "arima": 30.89743589743588,
            "lstm": 29.112903225806445,
            "actual_points": 20
        },
        {
            "name": "Edouard",
            "arima": 30.151515151515156,
            "lstm": 28.365384615384613,
            "actual_points": 27
        },
        {
            "name": "Lerma",
            "arima": 27.07317073170732,
            "lstm": 29.21875,
            "actual_points": 25
        }
    ],
    "EVE": [
        {
            "name": "A.Doucoure",
            "arima": 33.40505316077783,
            "lstm": 30.20325203252032,
            "actual_points": 49
        },
        {
            "name": "Tarkowski",
            "arima": 29.18840812223393,
            "lstm": 29.59183673469387,
            "actual_points": 31
        },
        {
            "name": "Pickford",
            "arima": 34.83516483516481,
            "lstm": 35.57650128774343,
            "actual_points": 41
        },
        {
            "name": "Calvert-Lewin",
            "arima": 34.44320626048201,
            "lstm": 34.921063040999215,
            "actual_points": 28
        },
        {
            "name": "McNeil",
            "arima": 31.3674364520485,
            "lstm": 29.39393939393939,
            "actual_points": 45
        },
        {
            "name": "Garner",
            "arima": 47.76100145211657,
            "lstm": 21.428571428571427,
            "actual_points": 22
        },
        {
            "name": "Branthwaite",
            "arima": 17.647058823529417,
            "lstm": 22.307692307692303,
            "actual_points": 33
        },
        {
            "name": "Harrison",
            "arima": 40.19047619047618,
            "lstm": 38.27393534450089,
            "actual_points": 32
        },
        {
            "name": "Mykolenko",
            "arima": 25.00000000000001,
            "lstm": 27.236842105263154,
            "actual_points": 51
        },
        {
            "name": "Onana",
            "arima": 23.230341522379838,
            "lstm": 26.833333333333332,
            "actual_points": 27
        }
    ],
    "FUL": [
        {
            "name": "Raúl",
            "arima": 15.281009414280643,
            "lstm": 37.59259259259259,
            "actual_points": 41
        },
        {
            "name": "Cairney",
            "arima": 20.126582278481,
            "lstm": 24.126984126984123,
            "actual_points": 37
        },
        {
            "name": "Iwobi",
            "arima": 26.45569620253166,
            "lstm": 27.93650793650794,
            "actual_points": 42
        },
        {
            "name": "Leno",
            "arima": 37.01381227286799,
            "lstm": 32.78761061946903,
            "actual_points": 28
        },
        {
            "name": "Wilson",
            "arima": 25.294117647058805,
            "lstm": 26.57407407407408,
            "actual_points": 33
        },
        {
            "name": "Castagne",
            "arima": 31.396527526549225,
            "lstm": 31.027397260273975,
            "actual_points": 22
        },
        {
            "name": "Robinson",
            "arima": 23.04347826086957,
            "lstm": 26.45454545454545,
            "actual_points": 28
        },
        {
            "name": "J.Palhinha",
            "arima": 24.75000000000001,
            "lstm": 25.78125,
            "actual_points": 28
        },
        {
            "name": "Andreas",
            "arima": 32.88673641091234,
            "lstm": 33.03030303030304,
            "actual_points": 36
        },
        {
            "name": "De Cordova-Reid",
            "arima": 29.388591908269525,
            "lstm": 26.06060606060606,
            "actual_points": 24
        },
        {
            "name": "Willian",
            "arima": 38.43750000000001,
            "lstm": 35.605733686307275,
            "actual_points": 49
        }
    ],
    "LIV": [
        {
            "name": "A.Becker",
            "arima": 43.470894370076174,
            "lstm": 36.34111393683696,
            "actual_points": 49
        },
        {
            "name": "Salah",
            "arima": 69.1758241758241,
            "lstm": 68.0415011377497,
            "actual_points": 73
        },
        {
            "name": "Alexander-Arnold",
            "arima": 52.44061364290537,
            "lstm": 46.47934767532275,
            "actual_points": 68
        },
        {
            "name": "Virgil",
            "arima": 48.53581569747084,
            "lstm": 41.55776163803437,
            "actual_points": 43
        },
        {
            "name": "Jones",
            "arima": 28.385850386699822,
            "lstm": 24.795918367346946,
            "actual_points": 20
        },
        {
            "name": "Konaté",
            "arima": 28.38709677419355,
            "lstm": 29.61994162640625,
            "actual_points": 30
        },
        {
            "name": "Luis Díaz",
            "arima": 34.57142857142856,
            "lstm": 36.415265370277695,
            "actual_points": 24
        },
        {
            "name": "Darwin",
            "arima": 40.27777777777778,
            "lstm": 31.428571428571427,
            "actual_points": 30
        },
        {
            "name": "Diogo J.",
            "arima": 37.82608695652173,
            "lstm": 37.738038086013006,
            "actual_points": 39
        },
        {
            "name": "Gakpo",
            "arima": 38.96855937751667,
            "lstm": 33.75,
            "actual_points": 21
        },
        {
            "name": "Szoboszlai",
            "arima": 0,
            "lstm": 0,
            "actual_points": 29
        },
        {
            "name": "Gomez",
            "arima": 0,
            "lstm": 0,
            "actual_points": 25
        }
    ],
    "LUT": [
        {
            "name": "Barkley",
            "arima": 28.180580996029,
            "lstm": 29.461538461538467,
            "actual_points": 35
        },
        {
            "name": "Kaminski",
            "arima": 0,
            "lstm": 0,
            "actual_points": 24
        },
        {
            "name": "Adebayo",
            "arima": 0,
            "lstm": 0,
            "actual_points": 27
        },
        {
            "name": "Ogbene",
            "arima": 0,
            "lstm": 0,
            "actual_points": 24
        },
        {
            "name": "Doughty",
            "arima": 0,
            "lstm": 0,
            "actual_points": 40
        },
        {
            "name": "Morris",
            "arima": 0,
            "lstm": 0,
            "actual_points": 24
        },
        {
            "name": "Brown",
            "arima": 0,
            "lstm": 0,
            "actual_points": 24
        }
    ],
    "MCI": [
        {
            "name": "Ederson M.",
            "arima": 38.986382525098385,
            "lstm": 34.61267605633803,
            "actual_points": 27
        },
        {
            "name": "Walker",
            "arima": 38.56060606060605,
            "lstm": 36.932897702080574,
            "actual_points": 26
        },
        {
            "name": "Aké",
            "arima": 32.583333333333336,
            "lstm": 29.84375,
            "actual_points": 35
        },
        {
            "name": "Foden",
            "arima": 45.27767620969967,
            "lstm": 42.181046265370284,
            "actual_points": 56
        },
        {
            "name": "Rodrigo",
            "arima": 30.220588235294095,
            "lstm": 30.002752379843006,
            "actual_points": 37
        },
        {
            "name": "Haaland",
            "arima": 82.34484918807516,
            "lstm": 81.30838268979758,
            "actual_points": 67
        },
        {
            "name": "Bernardo",
            "arima": 32.97297297297299,
            "lstm": 34.13430951092115,
            "actual_points": 60
        },
        {
            "name": "J.Alvarez",
            "arima": 36.842105263157904,
            "lstm": 27.66666666666666,
            "actual_points": 40
        },
        {
            "name": "Akanji",
            "arima": 32.25806451612903,
            "lstm": 28.75,
            "actual_points": 27
        },
        {
            "name": "Gvardiol",
            "arima": 0,
            "lstm": 0,
            "actual_points": 22
        }
    ],
    "MUN": [
        {
            "name": "Rashford",
            "arima": 45.489796150006896,
            "lstm": 38.15198157054349,
            "actual_points": 30
        },
        {
            "name": "McTominay",
            "arima": 25.15625,
            "lstm": 27.009803921568633,
            "actual_points": 34
        },
        {
            "name": "Lindelof",
            "arima": 29.984571264041023,
            "lstm": 30.648148148148152,
            "actual_points": 40
        },
        {
            "name": "Martial",
            "arima": 43.4579439252336,
            "lstm": 44.233474169092915,
            "actual_points": 21
        },
        {
            "name": "Evans",
            "arima": 31.333333333333332,
            "lstm": 31.5625,
            "actual_points": 20
        },
        {
            "name": "B.Fernandes",
            "arima": 44.00484471977619,
            "lstm": 44.33775024360333,
            "actual_points": 28
        },
        {
            "name": "Dalot",
            "arima": 36.56250000000001,
            "lstm": 33.202779308090165,
            "actual_points": 33
        },
        {
            "name": "Garnacho",
            "arima": 16.643994626009174,
            "lstm": 22.894736842105264,
            "actual_points": 44
        },
        {
            "name": "Onana",
            "arima": 0,
            "lstm": 0,
            "actual_points": 43
        },
        {
            "name": "Højlund",
            "arima": 0,
            "lstm": 0,
            "actual_points": 21
        }
    ],
    "NEW": [
        {
            "name": "Wilson",
            "arima": 45.60283687943261,
            "lstm": 37.589285714285715,
            "actual_points": 42
        },
        {
            "name": "Lascelles",
            "arima": 24.954954954954957,
            "lstm": 28.125,
            "actual_points": 30
        },
        {
            "name": "Trippier",
            "arima": 50.088681489081196,
            "lstm": 38.99999999999999,
            "actual_points": 36
        },
        {
            "name": "Longstaff",
            "arima": 29.936011069752166,
            "lstm": 25.597826086956523,
            "actual_points": 25
        },
        {
            "name": "Burn",
            "arima": 28.89763779527559,
            "lstm": 29.257425742574263,
            "actual_points": 43
        },
        {
            "name": "Joelinton",
            "arima": 25.467625899280563,
            "lstm": 26.261261261261264,
            "actual_points": 32
        },
        {
            "name": "Pope",
            "arima": 40.74667528007487,
            "lstm": 35.64814814814816,
            "actual_points": 47
        },
        {
            "name": "Gordon",
            "arima": 26.588047562191715,
            "lstm": 26.26865671641791,
            "actual_points": 50
        },
        {
            "name": "Bruno G.",
            "arima": 34.33962264150943,
            "lstm": 36.31485701437152,
            "actual_points": 24
        },
        {
            "name": "Almirón",
            "arima": 38.03081673707699,
            "lstm": 42.74304736231409,
            "actual_points": 30
        },
        {
            "name": "Isak",
            "arima": 46.800000000000004,
            "lstm": 40.93283453016217,
            "actual_points": 48
        }
    ],
    "NFO": [
        {
            "name": "Wood",
            "arima": 33.239728024904004,
            "lstm": 33.21969696969696,
            "actual_points": 51
        },
        {
            "name": "Gibbs-White",
            "arima": 31.015811782859796,
            "lstm": 25.833333333333332,
            "actual_points": 41
        },
        {
            "name": "Elanga",
            "arima": 25.90022254477772,
            "lstm": 24.86111111111111,
            "actual_points": 46
        },
        {
            "name": "Mangala",
            "arima": 18.529411764705884,
            "lstm": 23.518518518518515,
            "actual_points": 22
        },
        {
            "name": "Toffolo",
            "arima": 18.965619741306842,
            "lstm": 21.5625,
            "actual_points": 29
        },
        {
            "name": "Aina",
            "arima": 0,
            "lstm": 0,
            "actual_points": 27
        },
        {
            "name": "Turner",
            "arima": 0,
            "lstm": 0,
            "actual_points": 26
        },
        {
            "name": "Murillo",
            "arima": 0,
            "lstm": 0,
            "actual_points": 20
        }
    ],
    "SHU": [
        {
            "name": "Archer",
            "arima": 18.23529411764706,
            "lstm": 22.692307692307697,
            "actual_points": 34
        },
        {
            "name": "McAtee",
            "arima": 0,
            "lstm": 0,
            "actual_points": 28
        },
        {
            "name": "Foderingham",
            "arima": 0,
            "lstm": 0,
            "actual_points": 30
        },
        {
            "name": "Hamer",
            "arima": 0,
            "lstm": 0,
            "actual_points": 23
        }
    ],
    "TOT": [
        {
            "name": "Maddison",
            "arima": 43.45199193404002,
            "lstm": 42.03762411382087,
            "actual_points": 54
        },
        {
            "name": "Richarlison",
            "arima": 25.039454893437156,
            "lstm": 40.42860341986213,
            "actual_points": 53
        },
        {
            "name": "Romero",
            "arima": 30.78431372549019,
            "lstm": 28.000000000000004,
            "actual_points": 33
        },
        {
            "name": "Kulusevski",
            "arima": 38.00574847855886,
            "lstm": 40.34874194926169,
            "actual_points": 45
        },
        {
            "name": "Johnson",
            "arima": 29.09090909090908,
            "lstm": 30.42857142857143,
            "actual_points": 40
        },
        {
            "name": "Son",
            "arima": 50.66666666666668,
            "lstm": 44.36641794158897,
            "actual_points": 58
        },
        {
            "name": "Sarr",
            "arima": 20.000000000000004,
            "lstm": 23.333333333333332,
            "actual_points": 29
        },
        {
            "name": "Pedro Porro",
            "arima": 41.25000000000001,
            "lstm": 34.428555898924564,
            "actual_points": 37
        },
        {
            "name": "Udogie",
            "arima": 0,
            "lstm": 0,
            "actual_points": 21
        },
        {
            "name": "Vicario",
            "arima": 0,
            "lstm": 0,
            "actual_points": 25
        }
    ],
    "WHU": [
        {
            "name": "Ward-Prowse",
            "arima": 38.20343796284634,
            "lstm": 37.71598236706212,
            "actual_points": 41
        },
        {
            "name": "Zouma",
            "arima": 32.86764705882351,
            "lstm": 31.11111111111111,
            "actual_points": 26
        },
        {
            "name": "Emerson",
            "arima": 17.89473684210527,
            "lstm": 23.555555555555554,
            "actual_points": 34
        },
        {
            "name": "Bowen",
            "arima": 44.69230769230765,
            "lstm": 43.254337713721824,
            "actual_points": 53
        },
        {
            "name": "Areola",
            "arima": 32.608695652173914,
            "lstm": 31.38888888888889,
            "actual_points": 42
        },
        {
            "name": "L.Paquetá",
            "arima": 34.010898203455035,
            "lstm": 37.04706774911454,
            "actual_points": 40
        },
        {
            "name": "Coufal",
            "arima": 0,
            "lstm": 0,
            "actual_points": 29
        },
        {
            "name": "Souček",
            "arima": 0,
            "lstm": 0,
            "actual_points": 40
        },
        {
            "name": "Álvarez",
            "arima": 0,
            "lstm": 0,
            "actual_points": 24
        },
        {
            "name": "Kudus",
            "arima": 0,
            "lstm": 0,
            "actual_points": 64
        }
    ],
    "WOL": [
        {
            "name": "Lemina",
            "arima": 18.812221082898226,
            "lstm": 24.912280701754387,
            "actual_points": 45
        },
        {
            "name": "Kilman",
            "arima": 30.30927835051546,
            "lstm": 30.386781621284406,
            "actual_points": 29
        },
        {
            "name": "Dawson",
            "arima": 25.972331879270264,
            "lstm": 27.826086956521735,
            "actual_points": 37
        },
        {
            "name": "José Sá",
            "arima": 41.128864260993005,
            "lstm": 34.52385949903304,
            "actual_points": 23
        },
        {
            "name": "Toti",
            "arima": 22.14285714285715,
            "lstm": 25.22727272727273,
            "actual_points": 30
        },
        {
            "name": "Hee Chan",
            "arima": 54.13959358221688,
            "lstm": 26.379310344827584,
            "actual_points": 51
        },
        {
            "name": "Cunha",
            "arima": 26.296296296296298,
            "lstm": 25.952380952380953,
            "actual_points": 53
        },
        {
            "name": "Sarabia",
            "arima": 16.666666666666664,
            "lstm": 21.25,
            "actual_points": 39
        }
    ]
}